hack4u/__init__.py
hack4u/courses.py
hack4u/utils.py
ha4u-0.5.4444.dist-info/METADATA
ha4u-0.5.4444.dist-info/WHEEL
ha4u-0.5.4444.dist-info/top_level.txt
ha4u-0.5.4444.dist-info/RECORD
