Metadata-Version: 2.4
Name: ha4u
Version: 0.5.4444
Summary: Una biblioteca para consultar cursos de hack4u.
Home-page: https://hack4u.io
Author: Merovincio
Dynamic: author
Dynamic: description-content-type
Dynamic: home-page
Dynamic: summary
